[{"id": "WNQb9LVnxFDYCapX", "title": "parse time", "owner": "laboyteaux", "start": 1542066602811, "end": 1542068034671, "zone": 19}, {"id": "Y31jXbM6ChfwAQWp", "title": "eh", "owner": "laboyteaux", "start": 1541999719887, "end": 1542002134916, "zone": 19}, {"id": "kGhK64LaYpf3wcAJ", "title": "eh", "owner": "laboyteaux", "start": 1541999023540, "end": 1541999119171, "zone": -1}, {"id": "K6DJ9bCMHk3YGX8t", "title": "wed shennan", "owner": "kilaves", "start": 1540422399870, "end": 1540434374930, "zone": 19}, {"id": "NgvDRaP2Fxwyd8mZ", "title": "noble tues", "owner": "kilaves", "start": 1540335920893, "end": 1540347746660, "zone": 19}, {"id": "ZpVj8rtz7JX6AfbY", "title": "Heroic/Mythic Run", "owner": "laboyteaux", "start": 1539740006967, "end": 1539752368655, "zone": 19}, {"id": "9hnctqAbGZC3kjM8", "title": "noble tues repeat", "owner": "kilaves", "start": 1539729544090, "end": 1539739705393, "zone": 19}, {"id": "Yj9vAD8hmfLd4P2K", "title": "progression", "owner": "laboyteaux", "start": 1539308636941, "end": 1539320690493, "zone": 19}, {"id": "p438YVrHb6dJA7LZ", "title": "nbole tuhr suftf", "owner": "kilaves", "start": 1539297741489, "end": 1539300343274, "zone": -1}, {"id": "t93c8MwmrpRDAFnT", "title": "Progression", "owner": "laboyteaux", "start": 1539222655220, "end": 1539234207481, "zone": 19}, {"id": "tP46mxvhCqTyrZLB", "title": "noble wed stuff", "owner": "kilaves", "start": 1539211848687, "end": 1539221791905, "zone": 19}, {"id": "r8Wq71XTaQdpjgxL", "title": "Progression", "owner": "laboyteaux", "start": 1539134835988, "end": 1539147755840, "zone": 19}, {"id": "NCD3pGhT74M9xKtc", "title": "Heroic Zul", "owner": "Tresi", "start": 1539129524897, "end": 1539129716934, "zone": 19}, {"id": "vPGhJgDfKWM29Lz6", "title": "noble stuff tues", "owner": "kilaves", "start": 1539129821392, "end": 1539135308775, "zone": 19}, {"id": "m3kA6NMaLvQHCD12", "title": "noble stuff tuesday", "owner": "kilaves", "start": 1539125147822, "end": 1539129299206, "zone": 19}, {"id": "ZpdML93aGfDrwzRJ", "title": "Sanctuary Heroic/Mythic Progression", "owner": "laboyteaux", "start": 1539123846682, "end": 1539124911317, "zone": -1}, {"id": "tZdLDzVBT6fqmPYW", "title": "noble mother+", "owner": "kilaves", "start": 1538693005783, "end": 1538703518734, "zone": 19}, {"id": "qQAJ8aRhjpdVXcy9", "title": "noble wed stuff", "owner": "kilaves", "start": 1538606323893, "end": 1538617917324, "zone": 19}, {"id": "TnCcx34zVQJApFqL", "title": "nobles-before meeting", "owner": "kilaves", "start": 1538520298126, "end": 1538528392693, "zone": 19}, {"id": "1DFCA2rRcX78ZaWQ", "title": "noble mythic", "owner": "kilaves", "start": 1538089391702, "end": 1538099036168, "zone": 19}, {"id": "jZrwWY7MFtd684Hf", "title": "Nobels Heroic", "owner": "Tresi", "start": 1537916698914, "end": 1537926197444, "zone": 19}, {"id": "3zyXJRQ76Lk8mvZK", "title": "noble tues shennanigans", "owner": "kilaves", "start": 1537915749116, "end": 1537926188773, "zone": 19}, {"id": "q9XAFBckDQrJhTfG", "title": "noble ghuun", "owner": "kilaves", "start": 1537484191080, "end": 1537494282398, "zone": 19}, {"id": "XaxCvLY49AbBPKrM", "title": "nobles cont.....", "owner": "kilaves", "start": 1537397651474, "end": 1537406729269, "zone": 19}, {"id": "yLnVjD3qRmxB9hzM", "title": "noble heroic", "owner": "kilaves", "start": 1537311452868, "end": 1537322002894, "zone": 19}, {"id": "BvzdTqLpfnRGh12a", "title": "Normal Uldir", "owner": "Taehwaz", "start": 1537304100817, "end": 1537320021330, "zone": 19}, {"id": "FmtQczCjKn8GW7MX", "title": "noble third to last boss", "owner": "kilaves", "start": 1536878454744, "end": 1536889675115, "zone": 19}, {"id": "wLm1rczCDMPV6KfR", "title": "noble heroic wed", "owner": "kilaves", "start": 1536791771460, "end": 1536802999708, "zone": 19}, {"id": "8VKgLxF9vDkra2bw", "title": "herioc whats his face", "owner": "kilaves", "start": 1536278519167, "end": 1536284774828, "zone": 19}, {"id": "y3Pq942x6djJvFrT", "title": "Team 1 Heroic", "owner": "adrob", "start": 1536278651218, "end": 1536284074546, "zone": 19}, {"id": "XDCQmHqyMVx1AGvK", "title": "Heroic Team 1 09-06", "owner": "Tresi", "start": 1536278736505, "end": 1536284054239, "zone": 19}, {"id": "VJvLxyh4DY8QBG7R", "title": "heroic uldir", "owner": "kilaves", "start": 1536102492988, "end": 1536112795941, "zone": 19}, {"id": "CXLyY3P7dMHDkT8z", "title": "Heroic Uldir", "owner": "kilaves", "start": 1536102188887, "end": 1536103754926, "zone": 19}, {"id": "KjqJZv6Q2M4awyDV", "title": "arugssales", "owner": "kilaves", "start": 1531359361936, "end": 1531359837994, "zone": 17}, {"id": "Vtpa4BGrQqMvLH3j", "title": "arguscarries", "owner": "kilaves", "start": 1527122081498, "end": 1527128588592, "zone": 17}, {"id": "4m7XhrKkAaHMnLCd", "title": "arguscarries", "owner": "kilaves", "start": 1527125880508, "end": 1527126328570, "zone": 17}, {"id": "36PVJRmaMLnGrF7f", "title": "noblethur", "owner": "kilaves", "start": 1521760591673, "end": 1521770752076, "zone": 17}, {"id": "TDgb1PNYBZkd7AFp", "title": "nobleswed", "owner": "kilaves", "start": 1521673995511, "end": 1521684165642, "zone": 17}, {"id": "xM8JRgHf1BKNnpyb", "title": "noble tues", "owner": "kilaves", "start": 1520986528666, "end": 1520992912804, "zone": 17}, {"id": "HqpaBA6vjKZhDQCt", "title": "mythic noble wed", "owner": "kilaves", "start": 1521069221174, "end": 1521069221174, "zone": -1}, {"id": "gktV7F294aGnvZAC", "title": "mythic noble tues", "owner": "kilaves", "start": 1520986528666, "end": 1520987656583, "zone": 17}, {"id": "hnAdxVqacYKpQyPv", "title": "mythic noble tues", "owner": "kilaves", "start": 1521069115024, "end": 1521069115024, "zone": -1}, {"id": "XgZVA4T3YhHyJ8NM", "title": "noble keeper", "owner": "kilaves", "start": 1519950611638, "end": 1519959637494, "zone": 17}, {"id": "drTbCRzKcGYJH9Na", "title": "noblemythic", "owner": "kilaves", "start": 1519864959072, "end": 1519873525086, "zone": 17}, {"id": "26NMhaJAqT9bxBmd", "title": "noblemythic", "owner": "kilaves", "start": 1519777702351, "end": 1519786897657, "zone": 17}, {"id": "cHWL42JnrgjD3APk", "title": "noblemythic", "owner": "kilaves", "start": 1518568888167, "end": 1518573177844, "zone": 17}, {"id": "AY9qKZLRTgfFaJQM", "title": "tues heroic", "owner": "kilaves", "start": 1517961714806, "end": 1517970735246, "zone": 17}, {"id": "h1gW2ZxTMfKG9QCY", "title": "prepurchase killer", "owner": "kilaves", "start": 1517358375468, "end": 1517367942596, "zone": 17}, {"id": "Rg7Kbh1HYBcTFJXk", "title": "tues mythic", "owner": "kilaves", "start": 1516752924069, "end": 1516762246535, "zone": 17}, {"id": "p3mgN7n9C2JWvc1P", "title": "argus sales", "owner": "kilaves", "start": 1516323577453, "end": 1516325312054, "zone": 17}, {"id": "pWnDXRgtAbLdmcTf", "title": "nobles/wed", "owner": "kilaves", "start": 1516233387976, "end": 1516244734063, "zone": 17}, {"id": "4jCHwXmtn16PzvYT", "title": "nobletuesraid", "owner": "kilaves", "start": 1516148713846, "end": 1516157798907, "zone": 17}, {"id": "hg8pxwAXJZG71aPH", "title": "nobletuesraid", "owner": "kilaves", "start": 1516148593521, "end": 1516148593521, "zone": -1}, {"id": "ARpVtB8Nj9qTbQ6a", "title": "noble/wed", "owner": "kilaves", "start": 1515632075191, "end": 1515637920247, "zone": 17}, {"id": "AJhHBqMnGZ4WXmTF", "title": "noble/wed", "owner": "kilaves", "start": 1515630362091, "end": 1515630925251, "zone": 17}, {"id": "a6HM1KfC39zpFcZV", "title": "nobleheroic", "owner": "kilaves", "start": 1515539050808, "end": 1515548802154, "zone": 17}, {"id": "YnHXGjr6TvBdQwxM", "title": "noble argus/mythic", "owner": "kilaves", "start": 1515024038637, "end": 1515030727794, "zone": 17}, {"id": "bzCrjm6gDWG9XJZy", "title": "noble heroics", "owner": "kilaves", "start": 1514936855859, "end": 1514948772052, "zone": 17}, {"id": "rx6CZcNRWd4BKJ98", "title": "noblesprt2", "owner": "kilaves", "start": 1514419443738, "end": 1514429564238, "zone": 17}, {"id": "r63awcFCAnJmDb9q", "title": "noblesheroic", "owner": "kilaves", "start": 1514332060026, "end": 1514343292126, "zone": 17}, {"id": "LG6x1mgZcKq9X4w2", "title": "H Argus/Mythic", "owner": "kilaves", "start": 1513814671641, "end": 1513825242179, "zone": 17}, {"id": "8WRNL3HtTwV7Mrh2", "title": "Nobles tues", "owner": "kilaves", "start": 1513727775993, "end": 1513738590435, "zone": 17}, {"id": "Wh1KHFptcyDfrCL3", "title": "Antorus, The Burning Throne", "owner": "Plebstaah", "start": 1513463822482, "end": 1513464113333, "zone": 17}, {"id": "vKmqpgd94VCMBDaF", "title": "noble argus thurs", "owner": "kilaves", "start": 1513296363896, "end": 1513306820233, "zone": 17}, {"id": "Lz6DJcdQwbkFnVGZ", "title": "Antorus, The Burning Throne", "owner": "Plebstaah", "start": 1513219683390, "end": 1513220114157, "zone": 17}, {"id": "XZpzRdH8AbNKtqYm", "title": "Antorus, The Burning Throne", "owner": "Plebstaah", "start": 1513214646776, "end": 1513215124431, "zone": 17}, {"id": "qrDMAwtJ4VkhXNLv", "title": "Antorus, The Burning Throne", "owner": "Plebstaah", "start": 1513123087613, "end": 1513129763277, "zone": 17}, {"id": "X7pRxHDd6c2LWrMT", "title": "Antorus, The Burning Throne", "owner": "Plebstaah", "start": 1512958220656, "end": 1512958809826, "zone": 17}, {"id": "FLxCWRYkQ16bZjgn", "title": "Antorus, The Burning Throne", "owner": "Plebstaah", "start": 1512955541234, "end": 1512955922989, "zone": 17}, {"id": "2L6X7xzMPymVpr4C", "title": "Antorus, The Burning Throne", "owner": "Plebstaah", "start": 1512954851423, "end": 1512955242007, "zone": 17}, {"id": "A94ZdLwHrb7xWjFy", "title": "Antorus, The Burning Throne", "owner": "Plebstaah", "start": 1512947810134, "end": 1512954011701, "zone": 17}, {"id": "8drZnAM2ybQaXwRk", "title": "Aggramar", "owner": "Plebstaah", "start": 1512782052547, "end": 1512782474529, "zone": 17}, {"id": "tcz4jGqmYFJxXwga", "title": "Normal", "owner": "Plebstaah", "start": 1512774300546, "end": 1512778045803, "zone": 17}, {"id": "nCBaKfd6GZt2ymJ8", "title": "Nobles - Argus - 12-7-17", "owner": "Plebstaah", "start": 1512693707391, "end": 1512694431571, "zone": 17}, {"id": "ahnmH8gNdJMt3AvK", "title": "Nobes 12-5-17", "owner": "Plebstaah", "start": 1512518760029, "end": 1512529349569, "zone": 17}, {"id": "LdhWjgqzbryKk1Mv", "title": "Antorus, The Burning Throne", "owner": "Plebstaah", "start": 1511915696677, "end": 1511917064360, "zone": 17}, {"id": "CfVyQG4pKrF9RWz7", "title": "Antorus, The Burning Throne", "owner": "Plebstaah", "start": 1511914684077, "end": 1511914950114, "zone": 17}, {"id": "KF8VmDjP9Lvb2tqc", "title": "Normal Antorus Clear", "owner": "Plebstaah", "start": 1511889574755, "end": 1511903784989, "zone": 17}, {"id": "nyVg2FRP6Cw7HMTL", "title": "Antorus, The Burning Throne", "owner": "Plebstaah", "start": 1511889574755, "end": 1511898754469, "zone": 17}, {"id": "BaHxGvKQRYhwyr28", "title": "Antorus, The Burning Throne", "owner": "Plebstaah", "start": 1511889574755, "end": 1511893241514, "zone": 17}, {"id": "XjhrWmt16B9vHGDy", "title": "H ToS Alt Run", "owner": "Minyeo", "start": 1511575914279, "end": 1511585366753, "zone": 13}, {"id": "wZcfmCNv7gdh2nVG", "title": "Nobles ", "owner": "Plebstaah", "start": 1511395973609, "end": 1511406585330, "zone": 13}, {"id": "Nax7Y6dfDg3VJyjB", "title": "Tomb of Sargeras", "owner": "Plebstaah", "start": 1511402481998, "end": 1511405615803, "zone": 13}, {"id": "h7A4mRDMvwgVcYjr", "title": "Tomb of Sargeras", "owner": "Plebstaah", "start": 1511402481998, "end": 1511405287046, "zone": 13}, {"id": "fBdpjzayWqrvc8Yb", "title": "Tomb of Sargeras", "owner": "Plebstaah", "start": 1511399450429, "end": 1511399916132, "zone": 13}, {"id": "PfHLFV4wBGqR3tQ2", "title": "M Sisters", "owner": "Minyeo", "start": 1510877659491, "end": 1510883388703, "zone": 13}, {"id": "2A7cwa3F8jvKgXWP", "title": "Mythic low 11/01", "owner": "Spenblakes00", "start": 1509578247115, "end": 1509581245154, "zone": 13}, {"id": "yC34gZxMfzwYVT6R", "title": "heroic run 10/31", "owner": "Spenblakes00", "start": 1509490760874, "end": 1509495782036, "zone": 13}, {"id": "RANvDmh16LQtkfWr", "title": "ToS N & H", "owner": "Minyeo", "start": 1504037410270, "end": 1504056751696, "zone": 13}, {"id": "tqCDaBbgrZXkPmvM", "title": "Team 1 M Goroth", "owner": "Minyeo", "start": 1503617024664, "end": 1503625497153, "zone": 13}, {"id": "ZfzDFVPqpc4a3tRx", "title": "M Goroth wipeage team 1", "owner": "Minyeo", "start": 1503532952030, "end": 1503539589044, "zone": 13}, {"id": "96rbJzv7MLXCNK2g", "title": "M NH", "owner": "Minyeo", "start": 1503097898926, "end": 1503195541983, "zone": 11}, {"id": "vZbqt4WAPfKcV8zg", "title": "Team 1 Heroic ToS", "owner": "Minyeo", "start": 1502235092460, "end": 1502242976333, "zone": 13}, {"id": "V3hBb87NQnqv9fak", "title": "M NH", "owner": "Minyeo", "start": 1501975001706, "end": 1501982671745, "zone": 11}, {"id": "Q7t4G8JdK1AYgpVT", "title": "N ToS mismosh run", "owner": "Minyeo", "start": 1501887737358, "end": 1501895951731, "zone": 13}, {"id": "Rb3nQdNrVZgpyC4J", "title": "H KJ Team 1", "owner": "Minyeo", "start": 1501806493483, "end": 1501807018195, "zone": 13}, {"id": "DZqmRK7dpwfnbFMX", "title": "Team 1 H ToS", "owner": "Minyeo", "start": 1501626832029, "end": 1501632955890, "zone": 13}, {"id": "1R3WDMkVt2BxdPJb", "title": "N ToS ", "owner": "Minyeo", "start": 1501285380864, "end": 1501291377466, "zone": 13}, {"id": "pwya8T179Hr6Pnvm", "title": "H Avatar-KJ Team 1", "owner": "Minyeo", "start": 1501111686786, "end": 1501120170015, "zone": 13}, {"id": "fmZ3YkQjVF9pxvBH", "title": "H ToS Team 1", "owner": "Minyeo", "start": 1501023552768, "end": 1501032505460, "zone": 13}, {"id": "CMqgp68rP3QvaDXt", "title": "Team 1 ToS Maiden etc", "owner": "Minyeo", "start": 1500505266084, "end": 1500514614623, "zone": 13}, {"id": "K2bm86BMJPg9Xcjw", "title": "Team 1 H ToS", "owner": "Minyeo", "start": 1500420102745, "end": 1500428847579, "zone": 13}, {"id": "zaX8xQHB2NVF4dmK", "title": "Tomb of Sargeras", "owner": "regional", "start": 1499998229920, "end": 1500005604154, "zone": 13}, {"id": "dGmwrWzDVNqB7yhQ", "title": "H Avatar", "owner": "Minyeo", "start": 1499989186155, "end": 1499989631896, "zone": 13}, {"id": "vRnaVqGj96P8TWtH", "title": "Tomb of Sargeras", "owner": "regional", "start": 1499912039847, "end": 1499921371515, "zone": 13}, {"id": "MrvqyPnaYWG2A7kN", "title": "H NH July 12", "owner": "Minyeo", "start": 1499893529528, "end": 1499898630894, "zone": 11}, {"id": "h9D137rRmNCLFT4n", "title": "Tomb of Sargeras", "owner": "regional", "start": 1499826498091, "end": 1499836299882, "zone": 13}, {"id": "k6AVJMn1rfZgTDYd", "title": "Tomb of Sargeras", "owner": "regional", "start": 1499764914067, "end": 1499774267809, "zone": 13}, {"id": "BgFn16NKvrfYZym9", "title": "Tomb of Sargeras", "owner": "regional", "start": 1499764914067, "end": 1499771698050, "zone": 13}, {"id": "3MtTf7wPQ8rFLNkD", "title": "Tomb of Sargeras", "owner": "regional", "start": 1499764914067, "end": 1499769214008, "zone": 13}, {"id": "KPX1Zmzvngr76aDF", "title": "Tomb of Sargeras", "owner": "regional", "start": 1499566385696, "end": 1499572926150, "zone": 13}, {"id": "RZzdrCLGQv4wKVAW", "title": "The Nighthold", "owner": "regional", "start": 1499563049853, "end": 1499564893689, "zone": 11}, {"id": "p2dPnGkqca174FLT", "title": "Tomb of Sargeras", "owner": "regional", "start": 1499515214731, "end": 1499517152859, "zone": 13}, {"id": "7RMNdf2hXC8LqGrD", "title": "Tomb of Sargeras", "owner": "regional", "start": 1499480771714, "end": 1499489753060, "zone": 13}, {"id": "L7AKb3wTkR4tXZ8n", "title": "Tomb of Sargeras", "owner": "regional", "start": 1499393302773, "end": 1499402647074, "zone": 13}, {"id": "B2gCWytLDPkM9GNd", "title": "H ToS t3", "owner": "regional", "start": 1498874175445, "end": 1498883023906, "zone": 13}, {"id": "Cq2cVgKNJQDFyrTW", "title": "Tomb of Sargeras", "owner": "regional", "start": 1498702493439, "end": 1498711183145, "zone": 13}, {"id": "BZC24LpahJ7XDzgP", "title": "Tomb of Sargeras", "owner": "regional", "start": 1498615593888, "end": 1498628570044, "zone": 13}, {"id": "7Nw1RagFCBGjVrpT", "title": "Tomb of Sargeras", "owner": "regional", "start": 1498615593888, "end": 1498622279819, "zone": 13}, {"id": "7CxFB2mA39Ly8rNk", "title": "The Nighthold", "owner": "regional", "start": 1498554644971, "end": 1498555864055, "zone": 11}, {"id": "7Wv3KbZmjqG9Drf4", "title": "Tomb of Sargeras", "owner": "regional", "start": 1498447048054, "end": 1498453886143, "zone": 13}, {"id": "WVTgCArxkm1GnM9f", "title": "Tomb of Sargeras", "owner": "regional", "start": 1498357135851, "end": 1498369750686, "zone": 13}, {"id": "T2tNZphrfg4zDkyQ", "title": "Tomb of Sargeras", "owner": "regional", "start": 1498276338444, "end": 1498279561995, "zone": 13}, {"id": "F3qNJdKDLxB9HnwV", "title": "Tomb of Sargeras", "owner": "regional", "start": 1498271086987, "end": 1498274578044, "zone": 13}, {"id": "j2kMY1LDh8bPCfqa", "title": "Tomb of Sargeras", "owner": "regional", "start": 1498257590390, "end": 1498265348721, "zone": 13}, {"id": "R168BLTxgMh3qYDj", "title": "Tomb of Sargeras", "owner": "regional", "start": 1498183837705, "end": 1498195111476, "zone": 13}, {"id": "JCVGjWmnFPatRZqx", "title": "The Nighthold", "owner": "chiefgustavo000", "start": 1494396100014, "end": 1494475131127, "zone": 11}, {"id": "jqVptGgDv6TzahR1", "title": "The Nighthold", "owner": "chiefgustavo000", "start": 1494382799694, "end": 1494390028939, "zone": 11}, {"id": "vCxDNakzKVXYG63b", "title": "The Nighthold", "owner": "chiefgustavo000", "start": 1494038394464, "end": 1494044175364, "zone": 11}, {"id": "74DpwjdC8yKxLNzP", "title": "The Nighthold", "owner": "chiefgustavo000", "start": 1493172816199, "end": 1493188451999, "zone": 11}, {"id": "ctKdMAyfq6k1Naj8", "title": "The Nighthold", "owner": "chiefgustavo000", "start": 1493170525656, "end": 1493170815963, "zone": 11}, {"id": "JLyP1QAKkdxTh4qM", "title": "The Nighthold", "owner": "chiefgustavo000", "start": 1493167840701, "end": 1493168110782, "zone": 11}, {"id": "b78tKn4FdXDgATcj", "title": "Emerald Nightmare", "owner": "chiefgustavo000", "start": 1493077080834, "end": 1493166188007, "zone": 10}, {"id": "jwchg6p8BVN9mYKA", "title": "Trial of Valor", "owner": "chiefgustavo000", "start": 1492213305499, "end": 1492239348089, "zone": 12}, {"id": "tVCa9NWYyRzTc27d", "title": "Trial of Valor", "owner": "chiefgustavo000", "start": 1492211607256, "end": 1492212290489, "zone": 12}, {"id": "21tDLAbNyp9wkXja", "title": "The Nighthold", "owner": "chiefgustavo000", "start": 1492049514122, "end": 1492209566790, "zone": 11}, {"id": "Vk64KCPb3Xrq7hzB", "title": "The Nighthold", "owner": "chiefgustavo000", "start": 1492049499355, "end": 1492068664870, "zone": 11}, {"id": "KGNJca4jnBw9qFLk", "title": "The Nighthold", "owner": "chiefgustavo000", "start": 1492024767910, "end": 1492024951646, "zone": 11}, {"id": "aPCvy8KfT67kczMt", "title": "The Nighthold", "owner": "chiefgustavo000", "start": 1492021131458, "end": 1492024400963, "zone": 11}, {"id": "4JdgXhPVcYBKt36C", "title": "The Nighthold", "owner": "chiefgustavo000", "start": 1491963624985, "end": 1491973746892, "zone": 11}, {"id": "B7p9jKJPCaxYh6yZ", "title": "The Nighthold", "owner": "chiefgustavo000", "start": 1491947663201, "end": 1491951498963, "zone": 11}, {"id": "4jyJnGtrkPqDmac1", "title": "Trial of Valor", "owner": "chiefgustavo000", "start": 1491612272721, "end": 1491612568792, "zone": 12}, {"id": "jtZcgqhWLA3avNzT", "title": "The Nighthold", "owner": "chiefgustavo000", "start": 1491531092547, "end": 1491611400095, "zone": 11}, {"id": "ka2Y89c3TKtJXbLg", "title": "Unknown Zone", "owner": "chiefgustavo000", "start": 1491454379352, "end": 1491454379352, "zone": -1}, {"id": "WQMRxdXLrB9K3gak", "title": "The Nighthold", "owner": "chiefgustavo000", "start": 1491445096793, "end": 1491445453908, "zone": 11}, {"id": "fd8j3qw1VZBQNxMk", "title": "The Nighthold", "owner": "chiefgustavo000", "start": 1491445459624, "end": 1491451450115, "zone": 11}, {"id": "AZ78Frg2w6qxycXk", "title": "The Nighthold", "owner": "chiefgustavo000", "start": 1491358788258, "end": 1491369263526, "zone": 11}, {"id": "N8g1KfRXGz4YbjLd", "title": "The Nighthold", "owner": "chiefgustavo000", "start": 1491340664121, "end": 1491347173462, "zone": 11}, {"id": "xLFkGKt9dDcMwbf6", "title": "The Nighthold", "owner": "chiefgustavo000", "start": 1491340486567, "end": 1491340662373, "zone": 11}, {"id": "8a34ptny1fjFA69d", "title": "Emerald Nightmare", "owner": "chiefgustavo000", "start": 1491264306145, "end": 1491265203564, "zone": 10}, {"id": "bMFpahykwK6VzrgG", "title": "Emerald Nightmare", "owner": "chiefgustavo000", "start": 1491263585091, "end": 1491263974536, "zone": 10}, {"id": "43zw2hgJfm8LaCvY", "title": "Unknown Zone", "owner": "chiefgustavo000", "start": 1491263828939, "end": 1491263828939, "zone": -1}, {"id": "twVfrJNagczvy6Ck", "title": "Emerald Nightmare", "owner": "chiefgustavo000", "start": 1491262485568, "end": 1491263585091, "zone": 10}, {"id": "HMtYKZGzQ72CfFyR", "title": "Emerald Nightmare", "owner": "chiefgustavo000", "start": 1491262378938, "end": 1491262485568, "zone": 10}, {"id": "X9aZGjqD6dz2hV7x", "title": "The Nighthold", "owner": "chiefgustavo000", "start": 1490917489495, "end": 1490927644203, "zone": 11}, {"id": "Yg7RP4wnkHTMWX6y", "title": "The Nighthold", "owner": "chiefgustavo000", "start": 1490916246384, "end": 1490917155309, "zone": 11}, {"id": "wV4Zv3Q1jNq8M6hr", "title": "The Nighthold", "owner": "chiefgustavo000", "start": 1490915836220, "end": 1490916236619, "zone": 11}, {"id": "7H4bfK2ChGdvgtaM", "title": "Unknown Zone", "owner": "chiefgustavo000", "start": 1490823051211, "end": 1490823051211, "zone": -1}, {"id": "dy9PCjKJmQBWrDfN", "title": "Mythic Chronomatic Anomaly", "owner": "Muricateacup", "start": 1487304177635, "end": 1487310192427, "zone": 11}, {"id": "6xQVhDWGLdjKTv74", "title": "Normal NH", "owner": "shmashing", "start": 1486769262493, "end": 1486776758308, "zone": 11}, {"id": "CJxjnBLT8RvQpywM", "title": "Heroic Guldan", "owner": "shmashing", "start": 1486685428591, "end": 1486696953727, "zone": 11}, {"id": "Q7CBkmqRG9jfnrXL", "title": "Heroic NH", "owner": "shmashing", "start": 1486598640558, "end": 1486609646615, "zone": 11}, {"id": "6pX498WRFZmPqQtY", "title": "Heroic NH", "owner": "shmashing", "start": 1486513206729, "end": 1486523951055, "zone": 11}, {"id": "Dmkth4qHfdZCPyJG", "title": "Heroic NH", "owner": "shmashing", "start": 1486512947080, "end": 1486513206727, "zone": -1}, {"id": "AVj9Bp3d6rRWvFxZ", "title": "EN shenanigans FOR REAL", "owner": "shmashing", "start": 1486423042902, "end": 1486447864144, "zone": 10}, {"id": "yF89RfcvjtNgGPrw", "title": "Unknown Zone", "owner": "shmashing", "start": 1486422999473, "end": 1486422999473, "zone": -1}, {"id": "kmC8FXLnGbMp6Zcw", "title": "EN shennanigans", "owner": "shmashing", "start": 1486422193298, "end": 1486422193298, "zone": -1}, {"id": "h98FBjHxJPwpWfMR", "title": "EN shennanigans", "owner": "shmashing", "start": 1486419832380, "end": 1486419832380, "zone": -1}, {"id": "HJGyacvkRh3DmgpZ", "title": "ToV", "owner": "shmashing", "start": 1486169440555, "end": 1486174276581, "zone": 12}, {"id": "7FaQHpXA3qRCrhgj", "title": "Heroic Guldan lul", "owner": "shmashing", "start": 1486079638565, "end": 1486092584222, "zone": 11}, {"id": "zAapXJTNn8KVr2hG", "title": "Heroic NH", "owner": "shmashing", "start": 1485563626514, "end": 1485565210810, "zone": 11}, {"id": "ArPTCw4bMXf3nVHt", "title": "Heroic NH", "owner": "shmashing", "start": 1485393004752, "end": 1485400232409, "zone": 11}, {"id": "McVf46Lb3rAkCHhW", "title": "Heroic NH", "owner": "shmashing", "start": 1485303258260, "end": 1485314551149, "zone": 11}, {"id": "Kpfxj3mqkGydzgbR", "title": "Heroic NH", "owner": "shmashing", "start": 1484873015837, "end": 1484882265645, "zone": 11}, {"id": "c1NX8Bfg6RGCd9VD", "title": "Heroic NH", "owner": "shmashing", "start": 1484784278428, "end": 1484799744443, "zone": 11}, {"id": "TK4BJPXZRvM8qjn7", "title": "Heroic NH", "owner": "shmashing", "start": 1484698765980, "end": 1484709103834, "zone": 11}, {"id": "prc4QtbGfyMhdTF7", "title": "Heroic ToV", "owner": "shmashing", "start": 1484266539374, "end": 1484279442318, "zone": 12}, {"id": "LFZxVGp8jfXkPYAD", "title": "Mythic Xavius", "owner": "shmashing", "start": 1484185940622, "end": 1484199239449, "zone": 10}, {"id": "m8kbpdrZv1fy3QDN", "title": "Mythic EN", "owner": "shmashing", "start": 1484093150602, "end": 1484103649656, "zone": 10}, {"id": "PYfWaA87mtRr9xgz", "title": "Emerald Nightmare", "owner": "revion", "start": 1483567774154, "end": 1483585456020, "zone": 10}, {"id": "f9GTpNncQJYa7B38", "title": "Emerald Nightmare", "owner": "revion", "start": 1483482285094, "end": 1483498768451, "zone": 10}, {"id": "ZtQN4F9hmL7wgvx8", "title": "Trial of Valor", "owner": "revion", "start": 1483184071038, "end": 1483184611089, "zone": 12}, {"id": "TXL9QHRGNZPaAjnw", "title": "Emerald Nightmare", "owner": "revion", "start": 1483060707029, "end": 1483063827809, "zone": 10}, {"id": "Jfda4vk2MP1ZtpzX", "title": "Emerald Nightmare", "owner": "revion", "start": 1483060707029, "end": 1483063827809, "zone": 10}, {"id": "fLNGgWq9dAr86wkc", "title": "Mythic EN", "owner": "shmashing", "start": 1483489458477, "end": 1483498757645, "zone": 10}, {"id": "1AtGbJxMqmV6XQF9", "title": "Emerald Nightmare", "owner": "revion", "start": 1483056903678, "end": 1483059150633, "zone": 10}, {"id": "GnJ8tKTB7Xcr1adH", "title": "Emerald Nightmare", "owner": "revion", "start": 1483049817847, "end": 1483053975112, "zone": 10}, {"id": "xAkWzPDYNfr4pwV1", "title": "Emerald Nightmare", "owner": "revion", "start": 1482971000759, "end": 1482971273347, "zone": 10}, {"id": "2F6ZJGWaTdbk48Am", "title": "Emerald Nightmare", "owner": "revion", "start": 1482885279806, "end": 1482901508807, "zone": 10}, {"id": "wMtGfh1D32zbdyL6", "title": "Emerald Nightmare", "owner": "revion", "start": 1482290842047, "end": 1482297872991, "zone": 10}, {"id": "m6ndJCNZ4WzpXyjt", "title": "Emerald Nightmare", "owner": "revion", "start": 1482195410723, "end": 1482198673385, "zone": 10}, {"id": "a3Rg1ZJfqH2Nrcvx", "title": "Trial of Valor", "owner": "revion", "start": 1482022876963, "end": 1482040889076, "zone": 12}, {"id": "N7wXxcJDq6RtFLTW", "title": "Emerald Nightmare", "owner": "revion", "start": 1481959337694, "end": 1481959665394, "zone": 10}, {"id": "Mq39Rn8KhzmYrgba", "title": "Emerald Nightmare", "owner": "revion", "start": 1481859317886, "end": 1481865646495, "zone": 10}, {"id": "DrXMCHaTPNY4Bwxm", "title": "Emerald Nightmare", "owner": "revion", "start": 1481848363315, "end": 1481857525323, "zone": 10}, {"id": "DAJXRk6MFZbqcYvn", "title": "Emerald Nightmare", "owner": "revion", "start": 1481679798350, "end": 1481776022843, "zone": 10}, {"id": "tTxrGVw6MBj8aCK9", "title": "Emerald Nightmare", "owner": "revion", "start": 1481679798350, "end": 1481689863614, "zone": 10}, {"id": "yGpPavgwrQ1dWx3m", "title": "Emerald Nightmare", "owner": "revion", "start": 1481464924746, "end": 1481467924755, "zone": 10}, {"id": "Dg9NvKJTZP4wHtM1", "title": "Emerald Nightmare", "owner": "revion", "start": 1481247988768, "end": 1481262560943, "zone": 10}, {"id": "TqkRGp8Z7vayAnLQ", "title": "Emerald Nightmare", "owner": "revion", "start": 1481242266533, "end": 1481250741361, "zone": 10}, {"id": "4qYgQaNR7DC9W8pw", "title": "Emerald Nightmare", "owner": "revion", "start": 1481168057065, "end": 1481168247107, "zone": 10}, {"id": "yYVWCtnG8pcdJ1jb", "title": "Emerald Nightmare", "owner": "revion", "start": 1481080850099, "end": 1481089895989, "zone": 10}, {"id": "4x8DfLcbwBRCjhgq", "title": "Emerald Nightmare", "owner": "revion", "start": 1481069710154, "end": 1481077201383, "zone": 10}, {"id": "Wxf8CYQgAJRDjt73", "title": "Emerald Nightmare", "owner": "revion", "start": 1480763099610, "end": 1480996228316, "zone": 10}, {"id": "B9q24L6PRXtf1CQM", "title": "Emerald Nightmare", "owner": "revion", "start": 1480638058050, "end": 1480647591251, "zone": 10}, {"id": "VJrhLc3tGmDB1Kzn", "title": "Unknown Zone", "owner": "revion", "start": 1480465217291, "end": 1480481838703, "zone": -1}, {"id": "bYPyBvkMdHQZ7mW3", "title": "Trial of Valor", "owner": "revion", "start": 1479946559604, "end": 1479958626564, "zone": 12}, {"id": "fGHTcByDFp8M4wQ9", "title": "Emerald Nightmare", "owner": "revion", "start": 1479859731507, "end": 1479866335699, "zone": 10}, {"id": "8mw4hfPnjCM6p9Gy", "title": "Emerald Nightmare", "owner": "revion", "start": 1479691104742, "end": 1479702247876, "zone": 10}, {"id": "pXrYCMJRHxvmBqQ2", "title": "Emerald Nightmare", "owner": "revion", "start": 1479514561025, "end": 1479522856879, "zone": 10}, {"id": "QyPg8Bpa6nF7NKvC", "title": "Emerald Nightmare", "owner": "revion", "start": 1479343478167, "end": 1479346542675, "zone": 10}, {"id": "b4QvXCxjGPVW8T7H", "title": "Heroic EN", "owner": "shmashing", "start": 1480476359776, "end": 1480481834865, "zone": 10}, {"id": "ZFvy7tc9Yz8RhAjb", "title": "Mythic EN", "owner": "shmashing", "start": 1480473495426, "end": 1480473969503, "zone": 10}, {"id": "ztwGN7FjbgycdQnA", "title": "Mythic EN", "owner": "shmashing", "start": 1480465213928, "end": 1480468422813, "zone": 10}, {"id": "RbCtnyLhZm3Qdv6T", "title": "Mythic EN", "owner": "shmashing", "start": 1480378694191, "end": 1480386930755, "zone": 10}, {"id": "GcpraV2LRZfXPWAj", "title": "Emerald Nightmare", "owner": "revion", "start": 1479343478167, "end": 1479866335699, "zone": 10}, {"id": "WjPdLRpB63Fz4h9y", "title": "Emerald Nightmare", "owner": "revion", "start": 1479255211004, "end": 1479260356223, "zone": 10}]