[{"id": "q12Jb3Fy7vRtYzmk", "title": "Crucible of Storms", "owner": "shiraho94", "start": 1561683650161, "end": 1562123512859, "zone": 22}, {"id": "xCnMfmKWwX9yrA7R", "title": "Crucible of Storms", "owner": "ShinyTau", "start": 1561683875230, "end": 1561686923927, "zone": 22}, {"id": "kLXtGzBpyNKRYmVC", "title": "Battle of Dazar'alor", "owner": "shiraho94", "start": 1561511876090, "end": 1561519301469, "zone": 21}, {"id": "3hT2RdxX6w1zp98L", "title": "Battle of Dazar'alor", "owner": "ShinyTau", "start": 1561082429628, "end": 1561084760594, "zone": 21}, {"id": "XjALDvqnMgab38yH", "title": "Unknown Zone", "owner": "ShinyTau", "start": 1561082451730, "end": 1561082451730, "zone": -1}, {"id": "M1hcTwCaPqNvWpHQ", "title": "Battle of Dazar'alor", "owner": "ShinyTau", "start": 1560907146174, "end": 1560915731033, "zone": 21}, {"id": "NmpbkYCxBQRdPAZz", "title": "Unknown Zone", "owner": "ShinyTau", "start": 1560907174037, "end": 1560907174037, "zone": -1}, {"id": "GFBVKRzDjpJgaf2L", "title": "Battle of Dazar'alor", "owner": "ShinyTau", "start": 1560475896758, "end": 1560480793673, "zone": 21}, {"id": "RcCvKDjyZmwaLJgh", "title": "Battle of Dazar'alor", "owner": "Deathzaint", "start": 1559694470094, "end": 1559705751129, "zone": 21}, {"id": "8JA9dTcmnLWNjMky", "title": "Battle of Dazar'alor", "owner": "Deathzaint", "start": 1559867630593, "end": 1559877410208, "zone": 21}, {"id": "b6TYjF8tDfKVPk1a", "title": "Battle of Dazar'alor", "owner": "Deathzaint", "start": 1559867630593, "end": 1559870965695, "zone": 21}, {"id": "8NMd7z9CBKJ2Vbtg", "title": "Battle of Dazar'alor", "owner": "Deathzaint", "start": 1560045614614, "end": 1560058868246, "zone": 21}, {"id": "pjCwG8kWdNt4Mmya", "title": "Battle of Dazar'alor", "owner": "Deathzaint", "start": 1560299072434, "end": 1560309779767, "zone": 21}, {"id": "p7fYzBRy9qGhj3Pk", "title": "Mythic+ Dungeons", "owner": "Deathzaint", "start": 1560388035831, "end": 1560393594344, "zone": 20}, {"id": "AtqVWcDKBw69Rz4P", "title": "Unknown Zone", "owner": "ShinyTau", "start": 1560307257777, "end": 1560307302396, "zone": -1}]