[{"id": "q12Jb3Fy7vRtYzmk", "title": "Crucible of Storms", "owner": "shiraho94", "start": 1561683650161, "end": 1562123512859, "zone": 22}, {"id": "xCnMfmKWwX9yrA7R", "title": "Crucible of Storms", "owner": "ShinyTau", "start": 1561683875230, "end": 1561686923927, "zone": 22}, {"id": "kLXtGzBpyNKRYmVC", "title": "Battle of Dazar'alor", "owner": "shiraho94", "start": 1561511876090, "end": 1561519301469, "zone": 21}, {"id": "3hT2RdxX6w1zp98L", "title": "Battle of Dazar'alor", "owner": "ShinyTau", "start": 1561082429628, "end": 1561084760594, "zone": 21}, {"id": "XjALDvqnMgab38yH", "title": "Unknown Zone", "owner": "ShinyTau", "start": 1561082451730, "end": 1561082451730, "zone": -1}, {"id": "M1hcTwCaPqNvWpHQ", "title": "Battle of Dazar'alor", "owner": "ShinyTau", "start": 1560907146174, "end": 1560915731033, "zone": 21}, {"id": "NmpbkYCxBQRdPAZz", "title": "Unknown Zone", "owner": "ShinyTau", "start": 1560907174037, "end": 1560907174037, "zone": -1}, {"id": "GFBVKRzDjpJgaf2L", "title": "Battle of Dazar'alor", "owner": "ShinyTau", "start": 1560475896758, "end": 1560480793673, "zone": 21}, {"id": "RcCvKDjyZmwaLJgh", "title": "Battle of Dazar'alor", "owner": "Deathzaint", "start": 1559694470094, "end": 1559705751129, "zone": 21}, {"id": "8JA9dTcmnLWNjMky", "title": "Battle of Dazar'alor", "owner": "Deathzaint", "start": 1559867630593, "end": 1559877410208, "zone": 21}, {"id": "b6TYjF8tDfKVPk1a", "title": "Battle of Dazar'alor", "owner": "Deathzaint", "start": 1559867630593, "end": 1559870965695, "zone": 21}, {"id": "8NMd7z9CBKJ2Vbtg", "title": "Battle of Dazar'alor", "owner": "Deathzaint", "start": 1560045614614, "end": 1560058868246, "zone": 21}, {"id": "pjCwG8kWdNt4Mmya", "title": "Battle of Dazar'alor", "owner": "Deathzaint", "start": 1560299072434, "end": 1560309779767, "zone": 21}, {"id": "p7fYzBRy9qGhj3Pk", "title": "Mythic+ Dungeons", "owner": "Deathzaint", "start": 1560388035831, "end": 1560393594344, "zone": 20}, {"id": "AtqVWcDKBw69Rz4P", "title": "Unknown Zone", "owner": "ShinyTau", "start": 1560307257777, "end": 1560307302396, "zone": -1}, {"id": "8VY2a1xpXBkRZ4dn", "title": "Crucible of Storms", "owner": "shiraho94", "start": 1559869265943, "end": 1559879612065, "zone": 22}, {"id": "XA7r4wCJyLfnDjpt", "title": "Crucible of Storms", "owner": "ShinyTau", "start": 1559868604279, "end": 1559879502766, "zone": 22}, {"id": "tCK684T1ZNkjDfLV", "title": "Crucible of Storms", "owner": "shiraho94", "start": 1558660280150, "end": 1559098087313, "zone": 22}, {"id": "9hKZ2nXW1CgHYjxV", "title": "Unknown Zone", "owner": "shiraho94", "start": 1559098160805, "end": 1559098160805, "zone": -1}, {"id": "kbChvK4gf69y3Hqd", "title": "Battle of Dazar'alor", "owner": "Deathzaint", "start": 1558658214766, "end": 1558668728320, "zone": 21}, {"id": "xVQAgNvpLchzDqa2", "title": "Crucible of Storms", "owner": "shiraho94", "start": 1558660280150, "end": 1558668923293, "zone": 22}, {"id": "6CGpy4qTzBbxkFYM", "title": "Battle of Dazar'alor", "owner": "shiraho94", "start": 1558487147875, "end": 1558496828771, "zone": 21}, {"id": "YGM4k6P2Wmx3ntqa", "title": "Battle of Dazar'alor", "owner": "shiraho94", "start": 1558055081812, "end": 1558064809004, "zone": 21}, {"id": "DZM1dAQcHGBYnaFr", "title": "Battle of Dazar'alor", "owner": "shiraho94", "start": 1557882616267, "end": 1557891197372, "zone": 21}, {"id": "CjJ4dby2nWxVTNFD", "title": "Battle of Dazar'alor", "owner": "Deathzaint", "start": 1557613025230, "end": 1557622769029, "zone": 21}, {"id": "fk6TyzWdFQjCBDYX", "title": "Battle of Dazar'alor", "owner": "calfel", "start": 1557614727592, "end": 1557622752018, "zone": 21}, {"id": "z8rT92xQNkdAjGCR", "title": "Battle of Dazar'alor", "owner": "calfel", "start": 1557450790567, "end": 1557458063938, "zone": 21}, {"id": "t18B9bW64ky3M2zx", "title": "Mythic Opulence", "owner": "Deathzaint", "start": 1557450576914, "end": 1557458189847, "zone": 21}, {"id": "pJZWLmtQGNknMfcb", "title": "Battle of Dazar'alor", "owner": "Deathzaint", "start": 1557450576914, "end": 1557454359571, "zone": 21}, {"id": "RZ1qBXATtyxN32pv", "title": "Battle of Dazar'alor", "owner": "calfel", "start": 1557278504633, "end": 1557286536610, "zone": 21}, {"id": "cGCZQfBgFL8aDVrv", "title": "Battle of Dazar'alor", "owner": "shiraho94", "start": 1557277303864, "end": 1557286650051, "zone": 21}, {"id": "FKa6djHZ4ng7QbBN", "title": "Crucible of Storms", "owner": "calfel", "start": 1557028918914, "end": 1557030381824, "zone": 22}, {"id": "7WZqtyd4gMwJvDFY", "title": "Battle of Dazar'alor", "owner": "calfel", "start": 1557020474408, "end": 1557027403559, "zone": 21}, {"id": "1CYgWqrZk9P8BAN7", "title": "Battle of Dazar'alor", "owner": "calfel", "start": 1557020474408, "end": 1557020698407, "zone": 21}, {"id": "hTmWRF19kdvADYQK", "title": "Crucible of Storms", "owner": "calfel", "start": 1556933919702, "end": 1556936588487, "zone": 22}, {"id": "qGbW7r6hTjBJzLtR", "title": "H BoD alt night", "owner": "calfel", "start": 1556838797436, "end": 1556858053933, "zone": 20}, {"id": "yJ1Phkd4bzftW7Qa", "title": "Battle of Dazar'alor", "owner": "calfel", "start": 1555812008938, "end": 1555823954668, "zone": 21}, {"id": "t7cLBGgKbdC6jV9r", "title": "Battle of Dazar'alor", "owner": "calfel", "start": 1556068684528, "end": 1556077487477, "zone": 21}, {"id": "FDHjmr2f6hb1qXKv", "title": "Crucible of Storms", "owner": "calfel", "start": 1556156022198, "end": 1556158059204, "zone": 22}, {"id": "brfcTMBLqKQ8phYn", "title": "Crucible of Storms", "owner": "calfel", "start": 1556242258025, "end": 1556248057884, "zone": 22}, {"id": "NtbZBjQr3G1TDxhP", "title": "Battle of Dazar'alor", "owner": "calfel", "start": 1556323895213, "end": 1556344526029, "zone": 21}, {"id": "qW6QXVjcxgMf31wp", "title": "Mythic+ Dungeons", "owner": "calfel", "start": 1556379159060, "end": 1556407344056, "zone": 20}, {"id": "N9PyqtrcZMKRG3Tx", "title": "Mythic+ Dungeons", "owner": "calfel", "start": 1556489129079, "end": 1556513043630, "zone": 20}, {"id": "vCnLV2YBQW17agGF", "title": "Battle of Dazar'alor", "owner": "calfel", "start": 1556673625548, "end": 1556686164640, "zone": 21}, {"id": "WjQTLyMPD83qac4z", "title": "Battle of Dazar'alor", "owner": "shiraho94", "start": 1556673475979, "end": 1556680810794, "zone": 21}, {"id": "FAJ6QRNZxmLb3X8a", "title": "Crucible of Storms", "owner": "shiraho94", "start": 1556240758853, "end": 1556248219103, "zone": 22}, {"id": "94zYBxPLybmkWpJF", "title": "Battle of Dazar'alor", "owner": "Deathzaint", "start": 1556067359044, "end": 1556077076877, "zone": 21}, {"id": "97zm6VdJRAwc8xgF", "title": "Battle of Dazar'alor", "owner": "shiraho94", "start": 1555180493946, "end": 1556077713379, "zone": 21}, {"id": "GF3DzZ8pgVYWjNA4", "title": "Battle of Dazar'alor", "owner": "shiraho94", "start": 1555180493946, "end": 1556077710924, "zone": 21}, {"id": "L6gBxMWC4fdQhcvP", "title": "Battle of Dazar'alor", "owner": "shiraho94", "start": 1556073181308, "end": 1556077486405, "zone": 21}, {"id": "bQABDmx4vd1PL6an", "title": "Battle of Dazar'alor", "owner": "shiraho94", "start": 1556068542604, "end": 1556073181301, "zone": 21}, {"id": "8Zv9WXwkadycrfbD", "title": "Crucible of Storms", "owner": "Deathzaint", "start": 1555797832703, "end": 1555803656540, "zone": 22}, {"id": "yk1vbAHz28c6Rt7N", "title": "Battle of Dazar'alor", "owner": "calfel", "start": 1555733663913, "end": 1555744466872, "zone": 21}, {"id": "KQp4cX7WYF1Z6rjf", "title": "Murda's hc", "owner": "Deathzaint", "start": 1553983488252, "end": 1554006653882, "zone": 21}, {"id": "CgnJAXbHdjWm1QzD", "title": "Murda's hc", "owner": "Deathzaint", "start": 1553983488252, "end": 1554006653882, "zone": 21}, {"id": "2mJz917qt4ghGTQn", "title": "Crucible of Storms", "owner": "Deathzaint", "start": 1555637451301, "end": 1555645654289, "zone": 22}, {"id": "x1r9fwBTk2W4tYq6", "title": "Crucible of Storms", "owner": "Deathzaint", "start": 1555637451301, "end": 1555643551205, "zone": 22}, {"id": "tzPm6cbwvaGB3CX7", "title": "Crucible of Storms", "owner": "calfel", "start": 1555464413053, "end": 1555473650505, "zone": 22}, {"id": "DYcQCfH3wtGjFAvx", "title": "CoS", "owner": "Deathzaint", "start": 1555472288935, "end": 1555473693037, "zone": 22}, {"id": "PKVrgznaCBWcjfHv", "title": "CoS", "owner": "Deathzaint", "start": 1555470893929, "end": 1555470893929, "zone": -1}, {"id": "T8AVwdKy2a6n7NQ4", "title": "hre", "owner": "Deathzaint", "start": 1555280571028, "end": 1555289448997, "zone": 21}, {"id": "ArMjcKzpGkLZJND1", "title": "Battle of Dazar'alor", "owner": "shiraho94", "start": 1555031119171, "end": 1555040879794, "zone": 21}, {"id": "A1VFQgWzBhLaxr24", "title": "Battle of Dazar'alor", "owner": "shiraho94", "start": 1554858663823, "end": 1554867632257, "zone": 21}, {"id": "GcM1jVNfazBg6nt3", "title": "Battle of Dazar'alor", "owner": "shiraho94", "start": 1554337719227, "end": 1554436247474, "zone": 21}, {"id": "GJHTY7h9LbNK81FC", "title": "Battle of Dazar'alor", "owner": "shiraho94", "start": 1554429301638, "end": 1554436247474, "zone": 21}, {"id": "ZHXADxaFdty4nN9K", "title": "Battle of Dazar'alor", "owner": "shiraho94", "start": 1554253926183, "end": 1554262772088, "zone": 21}, {"id": "xPjXAnvQ2TWRDgJF", "title": "Battle of Dazar'alor", "owner": "shiraho94", "start": 1553910276600, "end": 1554253748432, "zone": 21}, {"id": "McJXtnC3PjYFHVb7", "title": "hc", "owner": "Deathzaint", "start": 1553983488252, "end": 1554006653882, "zone": 21}, {"id": "kcLb96RwDJjvyqgh", "title": "hc", "owner": "Deathzaint", "start": 1553915698419, "end": 1553917625959, "zone": 21}, {"id": "Y9qt4QWgnzVL7Pp8", "title": "Oppo", "owner": "Deathzaint", "start": 1553822817070, "end": 1553831072631, "zone": 21}, {"id": "4yCLZHDgmPbYz7NV", "title": "Battle of Dazar'alor", "owner": "shiraho94", "start": 1553822934701, "end": 1553831102932, "zone": 21}, {"id": "VPvrXJNMgADC8nKy", "title": "Battle of Dazar'alor", "owner": "shiraho94", "start": 1553648221580, "end": 1553658410893, "zone": 21}, {"id": "X2KjMNcZ1CHbgk9r", "title": "Battle of Dazar'alor", "owner": "shiraho94", "start": 1553655111378, "end": 1553658410893, "zone": 21}, {"id": "cHdBVpnKNGMYrC8T", "title": "Mythic", "owner": "Deathzaint", "start": 1553648304774, "end": 1553658353542, "zone": 21}, {"id": "NnY3Zc6zQFk4PW1B", "title": "Battle of Dazar'alor", "owner": "shiraho94", "start": 1553648294542, "end": 1553655098286, "zone": 21}, {"id": "1gHNqQbcyxJmtjhX", "title": "Unknown Zone", "owner": "shiraho94", "start": 1553480114694, "end": 1553480114694, "zone": -1}, {"id": "Dv7nwYQBg6taVK13", "title": "m", "owner": "Deathzaint", "start": 1553465881130, "end": 1553469458535, "zone": 21}, {"id": "kcMmxqWVyHz3FKwG", "title": "Battle of Dazar'alor", "owner": "shiraho94", "start": 1553384902728, "end": 1553392184654, "zone": 21}, {"id": "HBQ1ctNLC3rJw9Az", "title": "Battle of Dazar'alor", "owner": "shiraho94", "start": 1553381342173, "end": 1553384880512, "zone": 21}, {"id": "WN6dfkbDgc2MtYCj", "title": "Unknown Zone", "owner": "shiraho94", "start": 1553383354704, "end": 1553383354704, "zone": -1}, {"id": "CbMqjVQWcD6hHfLB", "title": "mythic", "owner": "Deathzaint", "start": 1553044343605, "end": 1553053711864, "zone": 21}, {"id": "pGFtN83zfYADa2Wr", "title": "?", "owner": "Deathzaint", "start": 1552255227970, "end": 1552262266962, "zone": 21}, {"id": "QvVzq2kRwWHtp1mn", "title": "?", "owner": "Deathzaint", "start": 1552353187194, "end": 1552363815981, "zone": 21}, {"id": "NxgHmtQBYDyvqGCJ", "title": "Battle of Dazar'alor", "owner": "shiraho94", "start": 1552451183668, "end": 1552620419478, "zone": 21}, {"id": "dKfZ7wJjGvhH6yTR", "title": "Battle of Dazar'alor", "owner": "shiraho94", "start": 1552438593209, "end": 1552449118232, "zone": 21}, {"id": "d4CVJfTX7gAnLzxc", "title": "Alliance?", "owner": "Deathzaint", "start": 1552353187194, "end": 1552363760735, "zone": 21}, {"id": "h7QYRdTDAZJMFwnm", "title": "Log horde 2", "owner": "Deathzaint", "start": 1552255227970, "end": 1552262266962, "zone": 21}, {"id": "KpktHcaVNRMxYj8v", "title": "Log horde 2", "owner": "Deathzaint", "start": 1552255227970, "end": 1552256889314, "zone": 21}, {"id": "Tdp7jfBL6nqt1QNZ", "title": "hrde hc", "owner": "Deathzaint", "start": 1552173789228, "end": 1552183552066, "zone": 21}, {"id": "hfdwqBJa2cVQN7K6", "title": "champs", "owner": "Deathzaint", "start": 1552172615867, "end": 1552173741330, "zone": 21}, {"id": "WP7vhQ8RmTDpLaXC", "title": "Battle of Dazar'alor", "owner": "shiraho94", "start": 1552010874131, "end": 1552023365226, "zone": 21}, {"id": "9tACzMPJL8r74Vpq", "title": "3/5", "owner": "shiraho94", "start": 1551837590804, "end": 1551847490186, "zone": 21}, {"id": "aPZdW6FLqTk8Hct1", "title": "mythic", "owner": "Deathzaint", "start": 1551745356829, "end": 1551756465384, "zone": 21}, {"id": "CNVt3AT72nDd9ZpY", "title": "Battle of Dazar'alor", "owner": "shiraho94", "start": 1551751617776, "end": 1551756502558, "zone": 21}, {"id": "VHNBA4qQ7ZKFhvnp", "title": "AOTC !!!", "owner": "Deathzaint", "start": 1551655268651, "end": 1551672856650, "zone": 21}, {"id": "L2g4yvCxXYhRtBFj", "title": "horde stuff", "owner": "Deathzaint", "start": 1551655268651, "end": 1551667736463, "zone": 21}, {"id": "AhLj2a6V7DYNGKMR", "title": "horde stuff", "owner": "Deathzaint", "start": 1551567842871, "end": 1551578213396, "zone": 21}, {"id": "wkt4H9yjqCMrh6mb", "title": "horde", "owner": "Deathzaint", "start": 1551567842871, "end": 1551574097660, "zone": 21}, {"id": "JBqWZd8cb2gPYaGf", "title": "Alliance Hc 1-5", "owner": "Deathzaint", "start": 1551227441203, "end": 1551243617654, "zone": 21}, {"id": "NbH2a4mhFyzBrCnQ", "title": "horde normal", "owner": "Deathzaint", "start": 1551227441203, "end": 1551228356603, "zone": 21}, {"id": "AxK1G3gRXrnWaLwM", "title": "horde", "owner": "Deathzaint", "start": 1550964055689, "end": 1550973494972, "zone": 21}, {"id": "YBQfF9tPhDbaV6r1", "title": "horde", "owner": "Deathzaint", "start": 1550963182955, "end": 1550963989082, "zone": 21}, {"id": "3XLBkdpWmHPNx9gt", "title": "alliance", "owner": "Deathzaint", "start": 1550803517387, "end": 1550808011753, "zone": 21}, {"id": "AZRjnJXCtL9azKwq", "title": "LAst two Normal", "owner": "Deathzaint", "start": 1550544896048, "end": 1550551003957, "zone": 21}, {"id": "6qk71tW4YAzxjdXF", "title": "horde", "owner": "Deathzaint", "start": 1550360909154, "end": 1550367397498, "zone": 21}, {"id": "bNK89Pg6Am2vXJpQ", "title": "horde", "owner": "Deathzaint", "start": 1550358342102, "end": 1550360594609, "zone": 21}, {"id": "6fhwBMxARYd2m7Xq", "title": "dasdsa", "owner": "Deathzaint", "start": 1550197559860, "end": 1550201495954, "zone": 21}, {"id": "PRkQY4K618nxWpGZ", "title": "Alliance 12th Feb", "owner": "Deathzaint", "start": 1550023731905, "end": 1550032405171, "zone": 21}, {"id": "Az1N9c6QfYh2FqPp", "title": "Jaina kill", "owner": "Deathzaint", "start": 1549937866878, "end": 1549949745416, "zone": 21}, {"id": "dV1rgyXFLMGhZTfQ", "title": "Stormwall", "owner": "Deathzaint", "start": 1549840371990, "end": 1549857727435, "zone": 21}, {"id": "RPzTdq1BxDZ8tKaw", "title": "Horde Nomal", "owner": "Deathzaint", "start": 1549840458290, "end": 1549850260484, "zone": 21}, {"id": "N9am6dYpG73PwZQn", "title": "Horde 9/02", "owner": "Deathzaint", "start": 1549753775143, "end": 1549763067794, "zone": 21}, {"id": "hYwF7tdZGXWDbLBa", "title": "Mythic Tries", "owner": "Deathzaint", "start": 1549592073099, "end": 1549600388349, "zone": 21}, {"id": "Q7Af1CPgHGwbcVpN", "title": "5th Feb", "owner": "Deathzaint", "start": 1549419449897, "end": 1549427528635, "zone": 21}, {"id": "x8jXZpDFJPGTCtbQ", "title": "THC", "owner": "Deathzaint", "start": 1548980742931, "end": 1548996402918, "zone": 20}, {"id": "1bmkxT37MnWgdQph", "title": "Normal", "owner": "Deathzaint", "start": 1548806891590, "end": 1548824571489, "zone": 20}, {"id": "CQmbY3pfZ67dT2tv", "title": "Rastakhan", "owner": "Deathzaint", "start": 1548629982378, "end": 1548637563827, "zone": 21}, {"id": "QfhWarc8YpKXxmwV", "title": "Council", "owner": "Deathzaint", "start": 1548629982378, "end": 1548633029906, "zone": 21}, {"id": "k9hTZyfGbWrM3Ppc", "title": "Normal BoD Tzuki", "owner": "Deathzaint", "start": 1548289929616, "end": 1548302500601, "zone": 20}, {"id": "GngR6v4jwCqB7tJy", "title": "Battle of Dazar'alor", "owner": "Deathzaint", "start": 1548197901821, "end": 1548225041765, "zone": 21}, {"id": "NaqdWHBJfw4hDkZb", "title": "Heoric BoD", "owner": "Deathzaint", "start": 1548197901821, "end": 1548218856229, "zone": 21}, {"id": "af6jDCmTwdprhgRL", "title": "Nomal BoD", "owner": "Deathzaint", "start": 1548197901821, "end": 1548205413176, "zone": 21}, {"id": "VWrQvt4CjBDaG7Ly", "title": "normal + hc", "owner": "Deathzaint", "start": 1547926399838, "end": 1547963631144, "zone": 19}, {"id": "Ax4t6YPDq8dGnBgX", "title": "mythrax horde twofists", "owner": "Deathzaint", "start": 1548016695537, "end": 1548019122209, "zone": 20}, {"id": "TwCMYxgVm62NAd4H", "title": "uldir", "owner": "Deathzaint", "start": 1547926399838, "end": 1547949991169, "zone": 19}, {"id": "axCQkrVZ9nDJKvgH", "title": "achv run", "owner": "Deathzaint", "start": 1547769659282, "end": 1547786356281, "zone": 19}, {"id": "xVmatp7M3NcCQ8nq", "title": "Horde raid", "owner": "Deathzaint", "start": 1547769659282, "end": 1547772798217, "zone": 19}, {"id": "fVWvNhaZ8qGbR1tn", "title": "15th Jan", "owner": "Deathzaint", "start": 1547597931077, "end": 1547610759985, "zone": 19}, {"id": "HFV6TzLmfaBZwMDh", "title": "HC ghuun", "owner": "Deathzaint", "start": 1547518538774, "end": 1547524102317, "zone": 19}, {"id": "ytZVfDYWkAz9pKnT", "title": "HC ghuun", "owner": "Deathzaint", "start": 1547000496244, "end": 1547006208011, "zone": 19}, {"id": "v9xDdKa874tmFzQw", "title": "random", "owner": "Deathzaint", "start": 1547000496244, "end": 1547006208011, "zone": 19}, {"id": "zHp2yAhbTcnXaV9x", "title": "random", "owner": "Deathzaint", "start": 1547172424505, "end": 1547178913737, "zone": 19}, {"id": "LGW3yrdA8cxDNkzC", "title": "hc 7/8", "owner": "Deathzaint", "start": 1547172424505, "end": 1547178913737, "zone": 19}, {"id": "cBXTKfzj6YhZVbFC", "title": "08 jan 2", "owner": "Deathzaint", "start": 1546913338624, "end": 1546921673378, "zone": 19}, {"id": "1aKWP3VXCJrkzbYQ", "title": "08 jan", "owner": "Deathzaint", "start": 1547000496244, "end": 1547006208011, "zone": 19}, {"id": "7CDv9kVFXN1TZ64w", "title": "Thursday Sept 27", "owner": "Durisx", "start": 1538095924012, "end": 1538104056784, "zone": 19}, {"id": "hR8HLPyZ6TM2Fr4t", "title": "H Uldir", "owner": "Cuddsieh", "start": 1537495511961, "end": 1537501060960, "zone": 19}, {"id": "pMTqWvF4LHDwjg8k", "title": "Uldir", "owner": "Cuddsieh", "start": 1537319024646, "end": 1537326578620, "zone": 19}, {"id": "FNmz2hGpdZnvD4Yf", "title": "H Uldir", "owner": "Cuddsieh", "start": 1536800296047, "end": 1536808602083, "zone": 19}, {"id": "qxHQD3aPpChTzBFg", "title": "Uldir", "owner": "Cuddsieh", "start": 1536717823105, "end": 1536724405238, "zone": 19}, {"id": "CXGYwPyb96cMzdBN", "title": "Uldir", "owner": "Cuddsieh", "start": 1536283086005, "end": 1536293990838, "zone": 19}, {"id": "aDR4dVJTpZ2BPtCy", "title": "Uldir", "owner": "Cuddsieh", "start": 1536196377981, "end": 1536205496770, "zone": 19}, {"id": "rQpwjN6ayRnAm7Jh", "title": "Uldir", "owner": "Cuddsieh", "start": 1536115531784, "end": 1536123149849, "zone": 19}, {"id": "nFrJXd8zyDjxQKHN", "title": "Antorus, The Burning Throne", "owner": "Cuddsieh", "start": 1533258934081, "end": 1533264844342, "zone": 17}, {"id": "RcH2JTC3NZ9mhFzD", "title": "Antorus, The Burning Throne", "owner": "Cuddsieh", "start": 1533087848832, "end": 1533092927175, "zone": 17}, {"id": "HLcXqCWtm6TV3MwK", "title": "Antorus, The Burning Throne", "owner": "Cuddsieh", "start": 1532480742906, "end": 1532489239964, "zone": 17}, {"id": "bHGYrq2ZjgX4LFVM", "title": "7/23 Heroic", "owner": "Cuddsieh", "start": 1532395353163, "end": 1532401674680, "zone": 17}, {"id": "L9fNhWcyxZ81pDK2", "title": "8.0 Test run", "owner": "Cuddsieh", "start": 1531885623557, "end": 1531891265955, "zone": 17}, {"id": "P9MgbJpq1NBHTyZF", "title": "Antorus, The Burning Throne", "owner": "Durisx", "start": 1530234176115, "end": 1530243194401, "zone": 17}, {"id": "97wYzNc83nJQTay1", "title": "june 26", "owner": "Durisx", "start": 1530060886556, "end": 1530070004285, "zone": 17}, {"id": "MTN8mAyD6kfxv9jC", "title": "Unknown Zone", "owner": "Durisx", "start": 1530061075922, "end": 1530067638148, "zone": -1}, {"id": "aqBnjAV2RFTmJ8PW", "title": "Antorus, The Burning Throne", "owner": "Durisx", "start": 1529629967637, "end": 1529639642766, "zone": 17}, {"id": "hGPdnyf3LcbW1xvV", "title": "June 19", "owner": "Durisx", "start": 1529458109131, "end": 1529463645917, "zone": 17}, {"id": "DGYwfB3RQFKn1Zxb", "title": "june 14", "owner": "Durisx", "start": 1529024757603, "end": 1529029913699, "zone": 17}, {"id": "kPpjbHaXWK4J8TLw", "title": "june 7", "owner": "Durisx", "start": 1528418637231, "end": 1528427914502, "zone": 17}, {"id": "tYgGQxfCBkmqPyNh", "title": "H ATB 5/24", "owner": "sethanbus", "start": 1527210072314, "end": 1527213863196, "zone": 17}, {"id": "GagykAVjqvL4pZP8", "title": "5/15 H-ATB", "owner": "sethanbus", "start": 1526432692921, "end": 1526440387891, "zone": 17}, {"id": "KcLyQxGNgHWpt86V", "title": "Norm Coven-Arg 5/10", "owner": "sethanbus", "start": 1526000339526, "end": 1526004667766, "zone": 17}, {"id": "bXtD7BjKJ8dYC9cp", "title": "H-ATB 5/8", "owner": "sethanbus", "start": 1525827343479, "end": 1525836508995, "zone": 17}, {"id": "pf894vygkTdaCRMb", "title": "N-Achieve Run (2)", "owner": "sethanbus", "start": 1524790222481, "end": 1524797536400, "zone": 17}, {"id": "9TcWamgM1JBZ6zPd", "title": "ATB Achieve Run(2)", "owner": "sethanbus", "start": 1524617705344, "end": 1524627525820, "zone": 17}, {"id": "XPmQWzLpy3jnKaVJ", "title": "Heroic 4/19", "owner": "sethanbus", "start": 1524185547007, "end": 1524193887085, "zone": 17}, {"id": "zMQpwGg9mNyrVkYD", "title": "Mythic", "owner": "sethanbus", "start": 1524012734507, "end": 1524022261192, "zone": 17}, {"id": "WD7TvkbyXZMBgFp8", "title": "Normal ", "owner": "sethanbus", "start": 1524009719899, "end": 1524011100695, "zone": 17}, {"id": "PjqHwXR2DWnJM6xy", "title": "43", "owner": "ChameleonX", "start": 1522803903068, "end": 1522812562342, "zone": 17}, {"id": "BtrYANCVf6mdyKkp", "title": "329Mythc", "owner": "ChameleonX", "start": 1522375141703, "end": 1522379111330, "zone": 17}, {"id": "6af2tnPYd94rFmJW", "title": "329", "owner": "ChameleonX", "start": 1522371636251, "end": 1522373600595, "zone": 17}, {"id": "6Gt3JHXBDPFcdznA", "title": "327", "owner": "ChameleonX", "start": 1522199552682, "end": 1522207847931, "zone": 17}, {"id": "YbhDwn3Qq7jxryJP", "title": "322", "owner": "ChameleonX", "start": 1521767275801, "end": 1521774919935, "zone": 17}, {"id": "r1nj67Bp2qL9GKyF", "title": "Antorus, The Burning Throne", "owner": "n3gotiator", "start": 1520990258493, "end": 1520998395568, "zone": 17}, {"id": "LMzq3T8ZnPJbdmhr", "title": "3-6-18", "owner": "ChameleonX", "start": 1520387935097, "end": 1520396594020, "zone": 17}, {"id": "CnHw781BcYKQXPN6", "title": "3/1", "owner": "ChameleonX", "start": 1519956605178, "end": 1519964858414, "zone": 17}, {"id": "VqmFvHj6fBgGcytX", "title": "2/27", "owner": "ChameleonX", "start": 1519783456908, "end": 1519792622034, "zone": 17}, {"id": "gGpL3Y9Tr8yjaZDW", "title": "2-22", "owner": "ChameleonX", "start": 1519351812914, "end": 1519359760800, "zone": 17}, {"id": "cCpjQHA3dGLtnag9", "title": "2/20", "owner": "ChameleonX", "start": 1519178593214, "end": 1519187384439, "zone": 17}, {"id": "qnJXAWtLHwmNRrM3", "title": "2-15", "owner": "ChameleonX", "start": 1518746929066, "end": 1518754102109, "zone": 17}, {"id": "d9Kr7R3NGmQbcpMJ", "title": "2/13", "owner": "ChameleonX", "start": 1518573943619, "end": 1518582776940, "zone": 17}, {"id": "yzAPYTKWLwaVr4nN", "title": "NewGroup1", "owner": "ChameleonX", "start": 1518141575235, "end": 1518150097872, "zone": 17}, {"id": "8L1pATRvkKZVX2HF", "title": "Antorus, The Burning Throne", "owner": "Cattiarra", "start": 1517969168227, "end": 1517969387061, "zone": 17}, {"id": "hgCpbZ26RV37xQTX", "title": "2/1", "owner": "ChameleonX", "start": 1517537655692, "end": 1517545228792, "zone": 17}, {"id": "v1THPZkYQcWbmR6q", "title": "1/25", "owner": "ChameleonX", "start": 1516932465925, "end": 1516941397596, "zone": 17}, {"id": "QTCa1fbdBrNDWxKH", "title": "Pug", "owner": "ChameleonX", "start": 1516813531109, "end": 1516815444885, "zone": 17}, {"id": "B7XtgNCJnTAp3aV4", "title": "1-23", "owner": "ChameleonX", "start": 1516759636260, "end": 1516767616522, "zone": 17}, {"id": "RfkDHaL9VyQJqg4X", "title": "1-18", "owner": "ChameleonX", "start": 1516327534354, "end": 1516335349699, "zone": 17}, {"id": "p3Jh4aTLmArvdz91", "title": "Antorus, The Burning Throne", "owner": "Corbaine", "start": 1516320906612, "end": 1516325518472, "zone": 17}, {"id": "xR3ZQMgz8dCF1JrP", "title": "Antorus, The Burning Throne", "owner": "Corbaine", "start": 1516154531208, "end": 1516163632691, "zone": 17}, {"id": "6wy4BHtRcFTGhPQV", "title": "1/11", "owner": "ChameleonX", "start": 1515722917846, "end": 1515731370259, "zone": 17}, {"id": "JxnT6YftAb9WQaz8", "title": "1-9", "owner": "ChameleonX", "start": 1515550494965, "end": 1515558126673, "zone": 17}, {"id": "zx9nDApjaXtLqgYV", "title": "1-4", "owner": "ChameleonX", "start": 1515117759784, "end": 1515125309769, "zone": 17}, {"id": "yRj19XnKYZzLth3M", "title": "1-2", "owner": "ChameleonX", "start": 1514945041786, "end": 1514953207151, "zone": 17}, {"id": "ptMPN1fWxaRJ3Akh", "title": "1230", "owner": "ChameleonX", "start": 1514686568249, "end": 1514688752793, "zone": 17}, {"id": "NybYRBCmWXrgT7ZH", "title": "12/21", "owner": "ChameleonX", "start": 1513908353758, "end": 1513917140715, "zone": 17}, {"id": "wc7mqPYMTghFt6A1", "title": "1219", "owner": "ChameleonX", "start": 1513735573013, "end": 1513742281052, "zone": 17}, {"id": "mKtdRMPn3qQGD2Wg", "title": "1214", "owner": "ChameleonX", "start": 1513303733506, "end": 1513311427072, "zone": 17}, {"id": "QF2rvfyqZ7T8zxgh", "title": "12/12", "owner": "ChameleonX", "start": 1513130557985, "end": 1513139846656, "zone": 17}, {"id": "jKXtxGmYV93RTA76", "title": "12/7", "owner": "ChameleonX", "start": 1512698897436, "end": 1512707565863, "zone": 17}, {"id": "pr27AjhxBDK6LdwT", "title": "12-5", "owner": "ChameleonX", "start": 1512525935242, "end": 1512535293999, "zone": 17}, {"id": "T8aFHVh9GrLYtB3f", "title": "Mythic+ 7.3", "owner": "Corbaine", "start": 1512102307706, "end": 1512104287396, "zone": 18}, {"id": "kNYftchHXyCbxDAm", "title": "Antorus, The Burning Throne", "owner": "Corbaine", "start": 1512098475973, "end": 1512101494300, "zone": 17}, {"id": "bFGgpvLx8jQAyf4M", "title": "Antorus, The Burning Throne", "owner": "Corbaine", "start": 1512093472938, "end": 1512097026596, "zone": 17}, {"id": "qkfBVMGTCy7RrDz2", "title": "Antorus", "owner": "ChameleonX", "start": 1512098479704, "end": 1512101498105, "zone": 17}, {"id": "Ac8xMBvnbmQkarC3", "title": "Antorus, The Burning Throne", "owner": "Corbaine", "start": 1511920925111, "end": 1511930022499, "zone": 17}, {"id": "CtXbAZyvhcp1QmHJ", "title": "LAST TOS EVER", "owner": "ChameleonX", "start": 1511318061067, "end": 1511323932402, "zone": 13}, {"id": "9RY6byLz7X4JhrVw", "title": "1116", "owner": "ChameleonX", "start": 1510890229320, "end": 1510890764728, "zone": 13}, {"id": "rmfGxNj9zFR6aYvD", "title": "Tomb of Sargeras", "owner": "ChameleonX", "start": 1510889966221, "end": 1510889996922, "zone": 13}, {"id": "P4FpMYAqmrB8v1tT", "title": "11/15", "owner": "ChameleonX", "start": 1510713087153, "end": 1510719649237, "zone": 13}, {"id": "DNhgYv1V8r9ZtyKb", "title": "119", "owner": "ChameleonX", "start": 1510281162891, "end": 1510283634214, "zone": 13}, {"id": "rG84A9t3xcvyMNqQ", "title": "117", "owner": "ChameleonX", "start": 1510108443378, "end": 1510115313959, "zone": 13}, {"id": "4aVnqXF6Y7jB1xZ8", "title": "11/3", "owner": "ChameleonX", "start": 1509672836423, "end": 1509679714518, "zone": 13}, {"id": "HPLDw1Y86RZzKTrj", "title": "10/26", "owner": "ChameleonX", "start": 1509068253314, "end": 1509073862079, "zone": 13}, {"id": "XwZzjxWY8bJ6rBkg", "title": "10/19", "owner": "ChameleonX", "start": 1508463704255, "end": 1508470036270, "zone": 13}, {"id": "pk1a4K8ctvj2CfDm", "title": "1012", "owner": "ChameleonX", "start": 1507858853797, "end": 1507861207537, "zone": 13}, {"id": "nHy8wrh2Vzt3qv6A", "title": "10/10", "owner": "ChameleonX", "start": 1507686057687, "end": 1507692074836, "zone": 13}, {"id": "XtBnApk1mdJMDjTb", "title": "Tomb of Sargeras", "owner": "ChameleonX", "start": 1507080602776, "end": 1507086945339, "zone": 13}, {"id": "nCvR1yqYVDWdTFfH", "title": "Tomb of Sargeras", "owner": "Corbaine", "start": 1506649429381, "end": 1506653533940, "zone": 13}, {"id": "Vt4HF7DLrqC2xBmz", "title": "926", "owner": "ChameleonX", "start": 1506475603121, "end": 1506482651120, "zone": 13}, {"id": "C6mzVDcMXhwT9RJP", "title": "9/21", "owner": "ChameleonX", "start": 1506040692584, "end": 1506045612556, "zone": 13}, {"id": "V1aQ7wvq6cd4tPLK", "title": "919", "owner": "ChameleonX", "start": 1505867692942, "end": 1505878278270, "zone": 13}, {"id": "xNW49D6CtqRYPVFg", "title": "914", "owner": "ChameleonX", "start": 1505435685081, "end": 1505445682654, "zone": 13}, {"id": "2NyhTrD3YXZHB81M", "title": "9/12", "owner": "ChameleonX", "start": 1505262784502, "end": 1505273085554, "zone": 13}, {"id": "8bR7KZ3XGVmrnqjg", "title": "9-7", "owner": "ChameleonX", "start": 1504832447516, "end": 1504839231309, "zone": 13}, {"id": "FdqyBaNXnGm1T9tv", "title": "9-5", "owner": "ChameleonX", "start": 1504658253737, "end": 1504667999732, "zone": 13}, {"id": "WTBwgJMRrvQtXHph", "title": "8/31", "owner": "ChameleonX", "start": 1504226511345, "end": 1504231763585, "zone": 13}, {"id": "wcx8ATjm4kvK6Fnz", "title": "8/30", "owner": "ChameleonX", "start": 1504053364416, "end": 1504063547920, "zone": 13}, {"id": "ngz8wh7YLm19yRQa", "title": "8-17", "owner": "ChameleonX", "start": 1503016608597, "end": 1503025941924, "zone": 13}, {"id": "zVd9g4vRFnkTLAWb", "title": "8-17", "owner": "ChameleonX", "start": 1503016608597, "end": 1503018630816, "zone": -1}, {"id": "9nga16KhpdXjPm8V", "title": "8-15", "owner": "ChameleonX", "start": 1502843752664, "end": 1502853437311, "zone": 13}, {"id": "TfwJz73AyRrHcWBt", "title": "8-15", "owner": "ChameleonX", "start": 1502843386866, "end": 1502843386866, "zone": -1}, {"id": "F2nbqHLvG7gDhcQj", "title": "8/10", "owner": "ChameleonX", "start": 1502411818110, "end": 1502421478550, "zone": 13}, {"id": "aGjqhKXxgMnPCTA1", "title": "8/8", "owner": "ChameleonX", "start": 1502239179678, "end": 1502248095656, "zone": 13}, {"id": "C84ZwVvLFxGY7Kad", "title": "8/3", "owner": "ChameleonX", "start": 1501805575706, "end": 1501816840636, "zone": 13}, {"id": "C97n2ywFgNaRq16G", "title": "8-01", "owner": "ChameleonX", "start": 1501633800437, "end": 1501643947870, "zone": 13}, {"id": "T8v9nWcBDq4jZbFp", "title": "727", "owner": "ChameleonX", "start": 1501201922574, "end": 1501211558560, "zone": 13}, {"id": "kRxD41wdQyMjPWrp", "title": "725", "owner": "ChameleonX", "start": 1501029218774, "end": 1501039551105, "zone": 13}, {"id": "HMfrnAwtXPRv14xV", "title": "720", "owner": "ChameleonX", "start": 1500597414025, "end": 1500605679250, "zone": 13}, {"id": "7nDj1yca2Rtrf9JV", "title": "7/18", "owner": "ChameleonX", "start": 1500424375330, "end": 1500434109412, "zone": 13}, {"id": "9c2YkLCvVrRhyBGt", "title": "713", "owner": "ChameleonX", "start": 1499992646850, "end": 1500004516536, "zone": 13}, {"id": "q8Q93VrhLyfBgz4K", "title": "7/11", "owner": "ChameleonX", "start": 1499829057283, "end": 1499829916096, "zone": 13}, {"id": "dtBKQ4fpnwhDzV3Z", "title": "7/6", "owner": "ChameleonX", "start": 1499391064875, "end": 1499401878869, "zone": 13}, {"id": "FbBJ24d7aMv8z1Ym", "title": "Tomb of Sargeras", "owner": "ChameleonX", "start": 1498781687720, "end": 1498793544451, "zone": 13}, {"id": "RNHCDKaZ3FAwc8YP", "title": "6/27", "owner": "ChameleonX", "start": 1498608480490, "end": 1498620550496, "zone": 13}, {"id": "cLa127zQFXD8h4WZ", "title": "ToS 2", "owner": "ChameleonX", "start": 1498176514181, "end": 1498188396109, "zone": 13}, {"id": "GmyK6NdFL1RbxhMn", "title": "ToS1", "owner": "ChameleonX", "start": 1498004070436, "end": 1498015149609, "zone": 13}, {"id": "2Ft8JgM7VDvrp36h", "title": "615", "owner": "ChameleonX", "start": 1497571988057, "end": 1497584265054, "zone": 11}, {"id": "gbVHX9dzphBYkwrC", "title": "1", "owner": "ChameleonX", "start": 1497399421938, "end": 1497408333806, "zone": 11}, {"id": "2dxJz8LWybwvH3cM", "title": "6-1x2", "owner": "ChameleonX", "start": 1496362564777, "end": 1496373812788, "zone": 11}, {"id": "kTGb6LwyJd3RN9j1", "title": "6-1", "owner": "ChameleonX", "start": 1495757951438, "end": 1495764306969, "zone": 11}, {"id": "NVgbGFZDAy3Wacm6", "title": "5/25", "owner": "ChameleonX", "start": 1495757951438, "end": 1495764306969, "zone": 11}, {"id": "FrZ3kXd8nyfqQjgp", "title": "5/23", "owner": "ChameleonX", "start": 1495585218099, "end": 1495597071387, "zone": 11}, {"id": "bWRjka7vmgh1qF3N", "title": "The Nighthold", "owner": "SpeedyMage", "start": 1494549725630, "end": 1494558350867, "zone": 11}, {"id": "mz8KaDAVJdG9tq1L", "title": "The Nighthold", "owner": "SpeedyMage", "start": 1494376756080, "end": 1494387202054, "zone": 11}, {"id": "pf6k8HAWd9hLqtzx", "title": "The Nighthold", "owner": "SpeedyMage", "start": 1493944660416, "end": 1493954533766, "zone": 11}, {"id": "HkhYaj2PDr3JC7Aw", "title": "The Nighthold", "owner": "SpeedyMage", "start": 1493772150638, "end": 1493782266074, "zone": 11}, {"id": "pXLjJtVwF6hW4CHv", "title": "The Nighthold", "owner": "SpeedyMage", "start": 1493341860613, "end": 1493348937983, "zone": 11}, {"id": "1mLBwrYvN4MQhygG", "title": "The Nighthold", "owner": "Sylvaelion", "start": 1492735831789, "end": 1492747433457, "zone": 11}, {"id": "wHdZPRmTcfKBr24Q", "title": "The Nighthold", "owner": "Sylvaelion", "start": 1492562385209, "end": 1492571903580, "zone": 11}, {"id": "qXRPgzhjbN2mVTc6", "title": "The Nighthold", "owner": "Sylvaelion", "start": 1492390744764, "end": 1492400079703, "zone": 11}, {"id": "y94xXj2HDBdCrfvg", "title": "The Nighthold", "owner": "Sylvaelion", "start": 1491957864588, "end": 1491967662860, "zone": 11}, {"id": "PHJBC76FLatNXA48", "title": "The Nighthold", "owner": "Sylvaelion", "start": 1491525787974, "end": 1491792791478, "zone": 11}, {"id": "zdrhtWPJn8vH1TXq", "title": "The Nighthold", "owner": "Sylvaelion", "start": 1491525787974, "end": 1491538234579, "zone": 11}, {"id": "W4grXy9ApKq6aCNd", "title": "The Nighthold", "owner": "Sylvaelion", "start": 1491352450722, "end": 1491362557822, "zone": 11}, {"id": "RLNFn2cJB1tA49G3", "title": "The Nighthold", "owner": "Sylvaelion", "start": 1490921297935, "end": 1490930861301, "zone": 11}, {"id": "2HZdVCYD7jX1ygqv", "title": "No Trash", "owner": "Sylvaelion", "start": 1490748081900, "end": 1490755834115, "zone": 11}, {"id": "QrhTpVRF8Lq2NyKt", "title": "The Nighthold", "owner": "Sylvaelion", "start": 1490660661895, "end": 1490662014378, "zone": 11}, {"id": "Rh3BWCcybFaLqkKn", "title": "The Nighthold", "owner": "Sylvaelion", "start": 1490747559626, "end": 1490755834115, "zone": 11}, {"id": "wYkfLmpdQxZhBG4C", "title": "The Nighthold", "owner": "Sylvaelion", "start": 1490316300349, "end": 1490324393305, "zone": 11}, {"id": "H7Yb16N2KnAX4Z3M", "title": "The Nighthold", "owner": "Sylvaelion", "start": 1489538742123, "end": 1489547472191, "zone": 11}, {"id": "vcrPX6J9h3fg17AV", "title": "The Nighthold", "owner": "Sylvaelion", "start": 1490143878092, "end": 1490150816315, "zone": 11}]